__init__.py
bf_vol_pre-0.0.4.dist-info/licenses/LICENSE
res/opto_predict_neu.pkl
res/opto_predict_svr.pkl
res/sc_X.pkl
res/sc_y.pkl
res/北扶logo图标.png
vol_pre/vol_pre.py
bf_vol_pre-0.0.4.dist-info/METADATA
bf_vol_pre-0.0.4.dist-info/WHEEL
bf_vol_pre-0.0.4.dist-info/top_level.txt
bf_vol_pre-0.0.4.dist-info/RECORD
