Metadata-Version: 2.4
Name: bf_vol_pre
Version: 0.0.4
Summary: A voltage prediction program
Author-email: hmy <hmycsu@163.com>
Maintainer-email: hmy <hmycsu@163.com>
License-Expression: MIT
Project-URL: Homepage, https://pypi.org/project/bf_vol_pre/
Project-URL: Documentation, https://readthedocs.org
Project-URL: Repository, https://github.com/me/spam.git
Project-URL: Issues, https://github.com/me/spam/issues
Project-URL: Changelog, https://github.com/me/spam/blob/master/CHANGELOG.md
Keywords: vol_pre,bf_vol_pre
Classifier: Development Status :: 3 - Alpha
Classifier: Intended Audience :: Developers
Classifier: Programming Language :: Python :: 3.12
Classifier: Operating System :: OS Independent
Requires-Python: >=3.9
License-File: LICENSE
Requires-Dist: joblib==1.4.2
Requires-Dist: numpy==2.2.5
Requires-Dist: scikit-learn==1.6.1
Requires-Dist: scipy==1.15.2
Requires-Dist: setuptools==79.0.0
Requires-Dist: threadpoolctl==3.6.0
Requires-Dist: wheel==0.45.1
Dynamic: license-file
